setup.cfg
setup.py
hackerrank/HackerRankAPI.py
hackerrank/__init__.py
hackerrank/settings.py
hackerrank/testing.py
hackerrank_sdk.egg-info/PKG-INFO
hackerrank_sdk.egg-info/SOURCES.txt
hackerrank_sdk.egg-info/dependency_links.txt
hackerrank_sdk.egg-info/top_level.txt